cli/__init__.py
cli/cms.py
cli/cms_config.py
cli/cms_util.py
sdc/__init__.py
sdc/capsule_manager_frame.py
sdc/error.py
sdc/crypto/__init__.py
sdc/crypto/asymm.py
sdc/crypto/symm.py
sdc/util/__init__.py
sdc/util/constants.py
sdc/util/crypto.py
sdc/util/file.py
sdc/util/tool.py
capsule_manager_sdk-0.2.0.dev20240805.dist-info/METADATA
capsule_manager_sdk-0.2.0.dev20240805.dist-info/WHEEL
capsule_manager_sdk-0.2.0.dev20240805.dist-info/entry_points.txt
capsule_manager_sdk-0.2.0.dev20240805.dist-info/top_level.txt
capsule_manager_sdk-0.2.0.dev20240805.dist-info/RECORD
