Metadata-Version: 2.1
Name: capsule-manager-sdk
Version: 0.2.0.dev20240805
Summary: Secure Data Capsule SDK for python
Home-page: https://github.com/secretflow/capsule-manager-sdk.git
Author: secretflow
Author-email: secretflow-contact@service.alipay.com
License: Apache 2.0
Classifier: Programming Language :: Python :: 3
Classifier: License :: OSI Approved :: Apache Software License
Classifier: Operating System :: POSIX :: Linux
Requires-Dist: cryptography >=41.0.2
Requires-Dist: grpcio ==1.62.1
Requires-Dist: ruamel.yaml ==0.18.6
Requires-Dist: click ==8.1.7
Requires-Dist: trustflow-verification ==0.3.0.dev20240801
